sparvi/__init__.py
sparvi/config.py
sparvi/version.py
sparvi/cli/__init__.py
sparvi/cli/dbt.py
sparvi/cli/main.py
sparvi/cli/profile.py
sparvi/cli/validate.py
sparvi/db/__init__.py
sparvi/db/adapters.py
sparvi/db/connection.py
sparvi/profiler/__init__.py
sparvi/profiler/profile_engine.py
sparvi/utils/__init__.py
sparvi/utils/db_utils.py
sparvi/utils/env.py
sparvi/validations/__init__.py
sparvi/validations/default_validations.py
sparvi/validations/validator.py
sparvi_core-0.7.2.dist-info/licenses/LICENSE
sparvi_core-0.7.2.dist-info/METADATA
sparvi_core-0.7.2.dist-info/WHEEL
sparvi_core-0.7.2.dist-info/entry_points.txt
sparvi_core-0.7.2.dist-info/top_level.txt
sparvi_core-0.7.2.dist-info/RECORD
